dash_chartist/DashChartist.py
dash_chartist/__init__.py
dash_chartist/_imports_.py
dash_chartist/dash_chartist.dev.js
dash_chartist/dash_chartist.dev.js.map
dash_chartist/dash_chartist.min.js
dash_chartist/dash_chartist.min.js.map
dash_chartist/metadata.json
dash_chartist/package-info.json
dash_chartist-0.0.5.dist-info/LICENSE
dash_chartist-0.0.5.dist-info/METADATA
dash_chartist-0.0.5.dist-info/WHEEL
dash_chartist-0.0.5.dist-info/top_level.txt
dash_chartist-0.0.5.dist-info/RECORD
