Metadata-Version: 2.1
Name: dash-chartist
Version: 0.0.5
Summary: Dash wrapper for chartist library
Home-page: UNKNOWN
Author: Stave Jones <jonesst2608@gmail.com>
License: MIT
Platform: UNKNOWN
Classifier: Framework :: Dash
License-File: LICENSE
